{"cameraMode":{"drawMode":0,"name":"Shaded","section":"Shading Mode"},"sceneLighting":true,"audioPlay":false,"sceneViewState":{"m_AlwaysRefresh":false,"showFog":true,"showSkybox":true,"showFlares":true,"showImageEffects":true,"showParticleSystems":true,"showVisualEffectGraphs":true,"m_FxEnabled":true},"in2DMode":false,"pivot":{"x":-6.564281463623047,"y":5.428051948547363,"z":-11.67490291595459},"rotation":{"x":-0.29744285345077517,"y":0.3935794234275818,"z":-0.13626644015312196,"w":-0.85909503698349},"size":12.12435531616211,"orthographic":false}